scrapy_patchright/__init__.py
scrapy_patchright/_utils.py
scrapy_patchright/handler.py
scrapy_patchright/headers.py
scrapy_patchright/memusage.py
scrapy_patchright/page.py
scrapy_patchright-0.0.50.dist-info/METADATA
scrapy_patchright-0.0.50.dist-info/WHEEL
scrapy_patchright-0.0.50.dist-info/RECORD
